regression_model/VERSION
regression_model/__init__.py
regression_model/config.yml
regression_model/pipeline.py
regression_model/predict.py
regression_model/scorecard.py
regression_model/train_pipeline.py
regression_model/config/__init__.py
regression_model/config/core.py
regression_model/datasets/__init__.py
regression_model/datasets/adjusted_data.csv
regression_model/datasets/dummy_train_columns.csv
regression_model/datasets/test.csv
regression_model/datasets/train.csv
regression_model/datasets/y_train.csv
regression_model/pipeline_processors/__init__.py
regression_model/pipeline_processors/transformers_dependencies.py
regression_model/processing/__init__.py
regression_model/processing/data_manager.py
regression_model/processing/features.py
regression_model/processing/validation.py
regression_model/trained_models/__init__.py
regression_model/trained_models/regression_model_output_v0.0.3.pkl
credit_risk_model_api-0.0.3.dist-info/LICENSE.txt
credit_risk_model_api-0.0.3.dist-info/METADATA
credit_risk_model_api-0.0.3.dist-info/WHEEL
credit_risk_model_api-0.0.3.dist-info/top_level.txt
credit_risk_model_api-0.0.3.dist-info/RECORD
